tap_shopify/__init__.py
tap_shopify/context.py
tap_shopify/exceptions.py
tap_shopify/schemas/abandoned_checkouts.json
tap_shopify/schemas/collects.json
tap_shopify/schemas/custom_collections.json
tap_shopify/schemas/customers.json
tap_shopify/schemas/definitions.json
tap_shopify/schemas/metafields.json
tap_shopify/schemas/order_refunds.json
tap_shopify/schemas/orders.json
tap_shopify/schemas/products.json
tap_shopify/schemas/transactions.json
tap_shopify/streams/__init__.py
tap_shopify/streams/abandoned_checkouts.py
tap_shopify/streams/base.py
tap_shopify/streams/collects.py
tap_shopify/streams/custom_collections.py
tap_shopify/streams/customers.py
tap_shopify/streams/metafields.py
tap_shopify/streams/order_refunds.py
tap_shopify/streams/orders.py
tap_shopify/streams/products.py
tap_shopify/streams/transactions.py
tap_shopify_velocity-1.7.0.dist-info/LICENSE
tap_shopify_velocity-1.7.0.dist-info/METADATA
tap_shopify_velocity-1.7.0.dist-info/WHEEL
tap_shopify_velocity-1.7.0.dist-info/entry_points.txt
tap_shopify_velocity-1.7.0.dist-info/top_level.txt
tap_shopify_velocity-1.7.0.dist-info/RECORD
